{"cameraMode":{"drawMode":0,"name":"Shaded","section":"Shading Mode"},"sceneLighting":true,"audioPlay":false,"sceneViewState":{"showFog":true,"showMaterialUpdate":false,"showSkybox":true,"showFlares":true,"showImageEffects":true,"showParticleSystems":true},"in2DMode":false,"pivot":{"x":111.68578338623047,"y":-122.83509063720703,"z":26.462726593017579},"rotation":{"x":-0.3129158318042755,"y":-0.575882077217102,"z":0.2532552480697632,"w":-0.7115579843521118},"size":184.458984375,"orthographic":false}