{"cameraMode":{"drawMode":0,"name":"Shaded","section":"Shading Mode"},"sceneLighting":true,"audioPlay":false,"sceneViewState":{"showFog":true,"showMaterialUpdate":false,"showSkybox":true,"showFlares":true,"showImageEffects":true,"showParticleSystems":true},"in2DMode":false,"pivot":{"x":102.89148712158203,"y":-100.93309783935547,"z":92.29693603515625},"rotation":{"x":-0.2841857075691223,"y":-0.40597689151763918,"z":0.1344534307718277,"w":-0.8581096529960632},"size":184.458984375,"orthographic":false}